eigenshuffle/__init__.py
eigenshuffle/eigenshuffle_functions.py
eigenshuffle/py.typed
eigenshuffle-0.1.3.dist-info/METADATA
eigenshuffle-0.1.3.dist-info/WHEEL
eigenshuffle-0.1.3.dist-info/licenses/LICENSE
eigenshuffle-0.1.3.dist-info/RECORD
