Metadata-Version: 2.4
Name: eigenshuffle
Version: 0.1.3
Summary: Keep consistent order of eigenvalues and eigenvectors of successive eigenvalue/vector problems based on the inital ordering of eigenvalues from low to high by matching closest eigenvectors and eigenvalues.
Project-URL: Repository, https://github.com/ograsdijk/eigenshuffle
Author-email: ograsdijk <o.grasdijk@gmail.com>
License-Expression: MIT
License-File: LICENSE
Requires-Python: ~=3.10
Requires-Dist: numpy<3,>=2.2.5
Requires-Dist: scipy<2,>=1.13.1
